{
	"ID"	:248,
	"name"	:"viewClass_viewSchedule_email_studentAccess_teacherAccess_updateRecord_addNewClass_updateClassDetail_viewRecord_monitorAttendanceStatus_accessCard",
	"vertices"	:[
		{
			"ID"	:0,
			"event"	:"["
		},
		{
			"ID"	:1,
			"event"	:"]"
		},
		{
			"ID"	:2,
			"event"	:"submit attendance"
		},
		{
			"ID"	:3,
			"event"	:"confirm your identity"
		},
		{
			"ID"	:4,
			"event"	:"log in"
		},
		{
			"ID"	:5,
			"event"	:"open notification settings"
		},
		{
			"ID"	:6,
			"event"	:"confirm notification settings"
		},
		{
			"ID"	:7,
			"event"	:"open class records"
		},
		{
			"ID"	:8,
			"event"	:"select the existing class"
		},
		{
			"ID"	:9,
			"event"	:"view class"
		},
		{
			"ID"	:10,
			"event"	:"select the existing schedule"
		},
		{
			"ID"	:11,
			"event"	:"view schedule"
		},
		{
			"ID"	:12,
			"event"	:"receive notifications as Email"
		},
		{
			"ID"	:13,
			"event"	:"access as a student"
		},
		{
			"ID"	:14,
			"event"	:"open my attendance records"
		},
		{
			"ID"	:15,
			"event"	:"access as a teacher"
		},
		{
			"ID"	:16,
			"event"	:"turn editing on"
		},
		{
			"ID"	:17,
			"event"	:"open student attendance records"
		},
		{
			"ID"	:18,
			"event"	:"select a class-list attendance record"
		},
		{
			"ID"	:19,
			"event"	:"select an editable student-record"
		},
		{
			"ID"	:20,
			"event"	:"submit attendance record update"
		},
		{
			"ID"	:21,
			"event"	:"edit attendance status"
		},
		{
			"ID"	:22,
			"event"	:"add new class"
		},
		{
			"ID"	:23,
			"event"	:"enter the name of the class"
		},
		{
			"ID"	:24,
			"event"	:"enter the class detail"
		},
		{
			"ID"	:25,
			"event"	:"submit the class"
		},
		{
			"ID"	:26,
			"event"	:"select the editable class"
		},
		{
			"ID"	:27,
			"event"	:"update the name of the class"
		},
		{
			"ID"	:28,
			"event"	:"update the class detail"
		},
		{
			"ID"	:29,
			"event"	:"select the existing record"
		},
		{
			"ID"	:30,
			"event"	:"view record"
		},
		{
			"ID"	:31,
			"event"	:"monitor current attendance status"
		},
		{
			"ID"	:32,
			"event"	:"read the access card to the card reader"
		}
			],
	"edges"	:[
		{
			"ID"	:0,
			"source"	:0,
			"target"	:2
		},
		{
			"ID"	:1,
			"source"	:3,
			"target"	:1
		},
		{
			"ID"	:2,
			"source"	:0,
			"target"	:4
		},
		{
			"ID"	:3,
			"source"	:4,
			"target"	:5
		},
		{
			"ID"	:4,
			"source"	:6,
			"target"	:1
		},
		{
			"ID"	:5,
			"source"	:8,
			"target"	:9
		},
		{
			"ID"	:6,
			"source"	:9,
			"target"	:1
		},
		{
			"ID"	:7,
			"source"	:7,
			"target"	:8
		},
		{
			"ID"	:8,
			"source"	:10,
			"target"	:11
		},
		{
			"ID"	:9,
			"source"	:11,
			"target"	:1
		},
		{
			"ID"	:10,
			"source"	:7,
			"target"	:10
		},
		{
			"ID"	:11,
			"source"	:5,
			"target"	:12
		},
		{
			"ID"	:12,
			"source"	:12,
			"target"	:6
		},
		{
			"ID"	:13,
			"source"	:13,
			"target"	:14
		},
		{
			"ID"	:14,
			"source"	:4,
			"target"	:13
		},
		{
			"ID"	:15,
			"source"	:13,
			"target"	:7
		},
		{
			"ID"	:16,
			"source"	:14,
			"target"	:7
		},
		{
			"ID"	:17,
			"source"	:4,
			"target"	:15
		},
		{
			"ID"	:18,
			"source"	:15,
			"target"	:16
		},
		{
			"ID"	:19,
			"source"	:16,
			"target"	:17
		},
		{
			"ID"	:20,
			"source"	:16,
			"target"	:7
		},
		{
			"ID"	:21,
			"source"	:17,
			"target"	:7
		},
		{
			"ID"	:22,
			"source"	:17,
			"target"	:18
		},
		{
			"ID"	:23,
			"source"	:17,
			"target"	:19
		},
		{
			"ID"	:24,
			"source"	:20,
			"target"	:1
		},
		{
			"ID"	:25,
			"source"	:18,
			"target"	:21
		},
		{
			"ID"	:26,
			"source"	:19,
			"target"	:21
		},
		{
			"ID"	:27,
			"source"	:21,
			"target"	:20
		},
		{
			"ID"	:28,
			"source"	:22,
			"target"	:23
		},
		{
			"ID"	:29,
			"source"	:23,
			"target"	:24
		},
		{
			"ID"	:30,
			"source"	:22,
			"target"	:24
		},
		{
			"ID"	:31,
			"source"	:24,
			"target"	:23
		},
		{
			"ID"	:32,
			"source"	:24,
			"target"	:25
		},
		{
			"ID"	:33,
			"source"	:23,
			"target"	:25
		},
		{
			"ID"	:34,
			"source"	:23,
			"target"	:23
		},
		{
			"ID"	:35,
			"source"	:24,
			"target"	:24
		},
		{
			"ID"	:36,
			"source"	:16,
			"target"	:22
		},
		{
			"ID"	:37,
			"source"	:25,
			"target"	:1
		},
		{
			"ID"	:38,
			"source"	:16,
			"target"	:26
		},
		{
			"ID"	:39,
			"source"	:27,
			"target"	:28
		},
		{
			"ID"	:40,
			"source"	:28,
			"target"	:27
		},
		{
			"ID"	:41,
			"source"	:27,
			"target"	:25
		},
		{
			"ID"	:42,
			"source"	:28,
			"target"	:25
		},
		{
			"ID"	:43,
			"source"	:27,
			"target"	:27
		},
		{
			"ID"	:44,
			"source"	:28,
			"target"	:28
		},
		{
			"ID"	:45,
			"source"	:26,
			"target"	:27
		},
		{
			"ID"	:46,
			"source"	:26,
			"target"	:28
		},
		{
			"ID"	:47,
			"source"	:29,
			"target"	:30
		},
		{
			"ID"	:48,
			"source"	:14,
			"target"	:29
		},
		{
			"ID"	:49,
			"source"	:30,
			"target"	:1
		},
		{
			"ID"	:50,
			"source"	:31,
			"target"	:1
		},
		{
			"ID"	:51,
			"source"	:14,
			"target"	:31
		},
		{
			"ID"	:52,
			"source"	:32,
			"target"	:32
		},
		{
			"ID"	:53,
			"source"	:2,
			"target"	:32
		},
		{
			"ID"	:54,
			"source"	:32,
			"target"	:3
		}
			]
}
